reloader_cli/__init__.py
reloader_cli/__main__.py
reloader_cli/exceptions.py
reloader_cli/formatter.py
reloader_cli-1.0.41.dist-info/LICENSE
reloader_cli-1.0.41.dist-info/METADATA
reloader_cli-1.0.41.dist-info/WHEEL
reloader_cli-1.0.41.dist-info/entry_points.txt
reloader_cli-1.0.41.dist-info/top_level.txt
reloader_cli-1.0.41.dist-info/RECORD
