Metadata-Version: 2.1
Name: reloader-cli
Version: 1.0.41
Summary: Help in fine tuning your changes with this minimalist CLI tool that reloads your python script after every save.
Author-email: Aman Ahmed Siddiqui <aasiddiqui40@gmail.com>
License: MIT License        
Project-URL: Homepage, https://github.com/sid-am-ahd935/reloader_cli
Keywords: debugger,reloader,cli_tool
Classifier: License :: OSI Approved :: MIT License
Classifier: Programming Language :: Python
Classifier: Programming Language :: Python :: 3
Requires-Python: >=3.8
License-File: LICENSE
Provides-Extra: build
Requires-Dist: twine ; extra == 'build'
Requires-Dist: build ; extra == 'build'
Provides-Extra: dev
Requires-Dist: black ; extra == 'dev'
Requires-Dist: pytest ; extra == 'dev'
Requires-Dist: coverage ; extra == 'dev'
